sentry_sms_ru
