Metadata-Version: 1.0
Name: sentry-sms-ru
Version: 0.0.3
Summary: A Sentry plugin that integrates with sms.ru
Home-page: https://bitbucket.org/silver_sky/sentry_sms_ru
Author: Yevgeniy Shchemelev
Author-email: shchemelevev@gmail.com
License: GPL
Platform: UNKNOWN
